http_jsonrpc/__init__.py
http_jsonrpc/http_jsonrpc.py
http_jsonrpc-0.1.5.dist-info/METADATA
http_jsonrpc-0.1.5.dist-info/WHEEL
http_jsonrpc-0.1.5.dist-info/RECORD
