Metadata-Version: 2.1
Name: http-jsonrpc
Version: 0.1.5
Summary: 
Author: Kamenlom
Author-email: ivashchenko.roman111@gmail.com
Requires-Python: >=3.8,<4.0
Classifier: Programming Language :: Python :: 3
Classifier: Programming Language :: Python :: 3.8
Classifier: Programming Language :: Python :: 3.9
Classifier: Programming Language :: Python :: 3.10
Classifier: Programming Language :: Python :: 3.11
Classifier: Programming Language :: Python :: 3.12
Requires-Dist: requests (>=2.27.1,<3.0.0)
